cc_core/__init__.py
cc_core/agent/__init__.py
cc_core/agent/__main__.py
cc_core/agent/main.py
cc_core/agent/restricted_red/__main__.py
cc_core/commons/__init__.py
cc_core/commons/cli_modes.py
cc_core/commons/command_builder.py
cc_core/commons/docker_utils.py
cc_core/commons/engines.py
cc_core/commons/exceptions.py
cc_core/commons/files.py
cc_core/commons/gpu_info.py
cc_core/commons/input_references.py
cc_core/commons/red.py
cc_core/commons/red_secrets.py
cc_core/commons/red_to_restricted_red.py
cc_core/commons/schema_map.py
cc_core/commons/schemas/__init__.py
cc_core/commons/schemas/auth.py
cc_core/commons/schemas/engines/__init__.py
cc_core/commons/schemas/engines/container.py
cc_core/commons/schemas/engines/execution.py
cc_core/version.py
cc_core-9.3.0.dist-info/LICENSE
cc_core-9.3.0.dist-info/METADATA
cc_core-9.3.0.dist-info/WHEEL
cc_core-9.3.0.dist-info/RECORD
