Metadata-Version: 2.1
Name: cc-core
Version: 9.3.0
Summary: CC-Core is part of the Curious Containers project. It contains shared code of the CC-FAICE and CC-Agency packages.
Home-page: https://www.curious-containers.cc/
License: AGPL-3.0
Author: Christoph Jansen
Author-email: Christoph.Jansen@htw-berlin.de
Requires-Python: >=3.7,<4.0
Classifier: License :: OSI Approved :: GNU Affero General Public License v3
Classifier: Programming Language :: Python :: 3
Classifier: Programming Language :: Python :: 3.7
Classifier: Programming Language :: Python :: 3.8
Classifier: Programming Language :: Python :: 3.9
Classifier: Programming Language :: Python :: 3.10
Classifier: Programming Language :: Python :: 3.11
Requires-Dist: docker (>=6.0,<7.0)
Requires-Dist: red-val (>=9.3,<9.4)
Requires-Dist: ruamel.yaml (>=0.17,<0.18)
Requires-Dist: urllib3 (>=1.26,<2.0)
Project-URL: Repository, https://github.com/curious-containers/cc-core
